{"stats":{"minecraft:custom":{"minecraft:jump":85,"minecraft:time_since_rest":4074,"minecraft:play_one_minute":12465,"minecraft:walk_one_cm":2486,"minecraft:leave_game":6,"minecraft:sprint_one_cm":5121,"minecraft:time_since_death":4027,"minecraft:walk_on_water_one_cm":27,"minecraft:deaths":1,"minecraft:sneak_time":6,"minecraft:drop":57,"minecraft:fly_one_cm":62711},"minecraft:picked_up":{"minecraft:red_sand":64},"minecraft:used":{"minecraft:dark_oak_planks":2},"minecraft:dropped":{"minecraft:dead_bush":1,"minecraft:bedrock":64,"minecraft:dark_oak_planks":1,"minecraft:red_sand":64}},"DataVersion":2586}